moten/__init__.py
moten/colorspace.py
moten/core.py
moten/extras.py
moten/io.py
moten/pyramids.py
moten/utils.py
moten/viz.py
pymoten-0.0.8.dist-info/LICENSE
pymoten-0.0.8.dist-info/METADATA
pymoten-0.0.8.dist-info/WHEEL
pymoten-0.0.8.dist-info/top_level.txt
pymoten-0.0.8.dist-info/RECORD
