Metadata-Version: 2.1
Name: pymoten
Version: 0.0.8
Summary: Extract motion energy features from video using spatio-temporal Gabors
Home-page: https://gallantlab.github.io/pymoten/
Author: Anwar O. Nunez-Elizalde
Author-email: anwarnunez@gmail.com
License: UNKNOWN
Platform: UNKNOWN
License-File: LICENSE
